pyedasc/__init__.py
pyedasc/ap.py
pyedasc/ca.py
pyedasc/mtp.py
pyedasc/rfi.py
pyedasc/tools.py
pyedasc-3.0.0.dist-info/LICENCE
pyedasc-3.0.0.dist-info/METADATA
pyedasc-3.0.0.dist-info/WHEEL
pyedasc-3.0.0.dist-info/top_level.txt
pyedasc-3.0.0.dist-info/RECORD
