Metadata-Version: 2.1
Name: pyedasc
Version: 3.0.0
Summary: Pyedasc is a collection of modules for analyzing different types of data from patch-clamp experiments.
Home-page: https://github.com/MS44neuro/pyedasc
Author: MS44neuro
Author-email: m.ghenghea@yahoo.com
Classifier: Programming Language :: Python :: 3
Classifier: License :: OSI Approved :: MIT License
Classifier: Operating System :: OS Independent
Requires-Python: >=3.8
License-File: LICENCE
